{
  "updatedAt": "2026-02-19T14:59:00-03:00",
  "items": [
    {
      "titulo": "Síndico executa corretora dentro e fora do prédio em execução premeditada, aponta polícia em Caldas Novas - ojornalismo",
      "texto": "Síndico executa corretora dentro e fora do prédio em execução premeditada, aponta polícia em Caldas Novas &nbsp;&nbsp; ojornalismo",
      "fonte": "news.google.com",
      "data": "19-02-2026"
    },
    {
      "titulo": "Vídeo gravado por corretora de imóveis mostra ataque de síndico em subsolo de prédio - Jornal do Tocantins",
      "texto": "Vídeo gravado por corretora de imóveis mostra ataque de síndico em subsolo de prédio &nbsp;&nbsp; Jornal do Tocantins",
      "fonte": "news.google.com",
      "data": "19-02-2026"
    },
    {
      "titulo": "Emboscada, pancada e tiros: veja como corretora foi morta por síndico - G1",
      "texto": "Emboscada, pancada e tiros: veja como corretora foi morta por síndico &nbsp;&nbsp; G1",
      "fonte": "news.google.com",
      "data": "19-02-2026"
    },
    {
      "titulo": "Em 43 minutos, síndico executou corretora com dois tiros e ocultou o corpo em GO, diz PCGO - Portal Contexto",
      "texto": "Em 43 minutos, síndico executou corretora com dois tiros e ocultou o corpo em GO, diz PCGO &nbsp;&nbsp; Portal Contexto",
      "fonte": "news.google.com",
      "data": "19-02-2026"
    }
  ]
}